{
  "resourceType": "ClinicalUseDefinition",
  "id": "DB00316-5742",
  "meta": {
    "profile": [
      "http://hl7.org/fhir/StructureDefinition/ClinicalUseDefinition"
    ],
    "lastUpdated": "2026-03-09T14:22:14.711415+00:00"
  },
  "type": "indication",
  "subject": [
    {
      "reference": "MedicationKnowledge/DB00316",
      "display": "Dynapayne"
    }
  ],
  "indication": {
    "diseaseSymptomProcedure": {
      "coding": [
        {
          "system": "http://purl.obolibrary.org/obo/mondo.owl",
          "code": "5742",
          "display": "emphysematous cholecystitis"
        }
      ],
      "text": "emphysematous cholecystitis"
    }
  },
  "extension": [
    {
      "url": "https://zatxgnn.yao.care/fhir/StructureDefinition/prediction-source",
      "valueString": "TxGNN-KG"
    },
    {
      "url": "https://zatxgnn.yao.care/fhir/StructureDefinition/research-only",
      "valueBoolean": true
    }
  ]
}