{
  "resourceType": "ClinicalUseDefinition",
  "id": "DB00316-20676",
  "meta": {
    "profile": [
      "http://hl7.org/fhir/StructureDefinition/ClinicalUseDefinition"
    ],
    "lastUpdated": "2026-03-09T14:22:06.007755+00:00"
  },
  "type": "indication",
  "subject": [
    {
      "reference": "MedicationKnowledge/DB00316",
      "display": "Dynapayne"
    }
  ],
  "indication": {
    "diseaseSymptomProcedure": {
      "coding": [
        {
          "system": "http://purl.obolibrary.org/obo/mondo.owl",
          "code": "20676",
          "display": "disease of central nervous system or retinal vasculature"
        }
      ],
      "text": "disease of central nervous system or retinal vasculature"
    }
  },
  "extension": [
    {
      "url": "https://zatxgnn.yao.care/fhir/StructureDefinition/prediction-source",
      "valueString": "TxGNN-KG"
    },
    {
      "url": "https://zatxgnn.yao.care/fhir/StructureDefinition/research-only",
      "valueBoolean": true
    }
  ]
}