{
  "resourceType": "ClinicalUseDefinition",
  "id": "DB01069-10080_16394_15518",
  "meta": {
    "profile": [
      "http://hl7.org/fhir/StructureDefinition/ClinicalUseDefinition"
    ],
    "lastUpdated": "2026-03-09T14:22:28.955600+00:00"
  },
  "type": "indication",
  "subject": [
    {
      "reference": "MedicationKnowledge/DB01069",
      "display": "Brunacod"
    }
  ],
  "indication": {
    "diseaseSymptomProcedure": {
      "coding": [
        {
          "system": "http://purl.obolibrary.org/obo/mondo.owl",
          "code": "10080_16394_15518",
          "display": "infantile bilateral striatal necrosis"
        }
      ],
      "text": "infantile bilateral striatal necrosis"
    }
  },
  "extension": [
    {
      "url": "https://zatxgnn.yao.care/fhir/StructureDefinition/prediction-source",
      "valueString": "TxGNN-KG"
    },
    {
      "url": "https://zatxgnn.yao.care/fhir/StructureDefinition/research-only",
      "valueBoolean": true
    }
  ]
}